<?xml version="1.0" encoding="UTF-8"?>
<con:soapui-project id="c822f5c5-2ec6-4485-b2d4-60b9a5242acc" activeEnvironment="Default" name="Save" soapui-version="5.2.1" abortOnError="false" runType="SEQUENTIAL" xmlns:con="http://eviware.com/soapui/config"><con:settings/><con:interface xsi:type="con:RestService" id="84f61ad1-dcde-4d75-ad3c-bbae711f0591" wadlVersion="http://wadl.dev.java.net/2009/02" name="http://localhost:52618" type="rest" xmlns:xsi="http://www.w3.org/2001/XMLSchema-instance"><con:settings/><con:definitionCache/><con:endpoints><con:endpoint>http://localhost:52618</con:endpoint></con:endpoints><con:resource name="Visits" path="/api/Visits/" id="fff2f4ee-ed13-4d6f-b54d-e1204b9efd08"><con:settings/><con:parameters/><con:method name="Visits" id="2a85809e-4870-44ec-8672-53038044cc26" method="POST"><con:settings/><con:parameters/><con:representation type="REQUEST"><con:mediaType>application/json</con:mediaType><con:params/></con:representation><con:representation type="FAULT"><con:mediaType>application/json; charset=utf-8</con:mediaType><con:status>400 405 500</con:status><con:params/><con:element xmlns:vis="http://localhost/api/Visits/">vis:Fault</con:element></con:representation><con:representation type="RESPONSE"><con:mediaType>application/json; charset=utf-8</con:mediaType><con:status>201 200</con:status><con:params/><con:element xmlns:vis="http://localhost/api/Visits/">vis:Response</con:element></con:representation><con:representation type="RESPONSE"><con:mediaType xsi:nil="true"/><con:status>200</con:status><con:params/><con:element>data</con:element></con:representation><con:representation type="RESPONSE"><con:mediaType xsi:nil="true"/><con:status>0</con:status><con:params/><con:element>data</con:element></con:representation><con:representation type="RESPONSE"><con:mediaType xsi:nil="true"/><con:status>200</con:status><con:params/><con:element>data</con:element></con:representation><con:representation type="RESPONSE"><con:mediaType xsi:nil="true"/><con:status>0</con:status><con:params/><con:element>data</con:element></con:representation><con:representation type="RESPONSE"><con:mediaType xsi:nil="true"/><con:status>200</con:status><con:params/><con:element>data</con:element></con:representation><con:representation type="RESPONSE"><con:mediaType xsi:nil="true"/><con:status>200</con:status><con:params/><con:element>data</con:element></con:representation><con:request name="Save" id="0505a6a3-71c6-4f9e-8133-717753a2a39f" mediaType="application/json" postQueryString="false"><con:settings><con:setting id="com.eviware.soapui.impl.wsdl.WsdlRequest@request-headers">&lt;xml-fragment/></con:setting></con:settings><con:endpoint>http://localhost:52618</con:endpoint><con:request>{"Id":"210523aa-ba60-4045-9842-d5d4b397bf09","VisitorId":"d807ef6b-15bd-463d-b97e-a6ffcf92a480","VisitDate":"2017-10-29T15:25:37.673", "CreatedDate":"2017-10-29T15:25:37.673"}</con:request><con:originalUri>http://localhost/api/Visits/</con:originalUri><con:credentials><con:authType>No Authorization</con:authType></con:credentials><con:jmsConfig JMSDeliveryMode="PERSISTENT"/><con:jmsPropertyConfig/><con:parameters/><con:parameterOrder/></con:request></con:method></con:resource></con:interface><con:properties/><con:wssContainer/><con:oAuth2ProfileContainer/></con:soapui-project>